mysql_db_backup_faster/Helper.py
mysql_db_backup_faster/Logger.py
mysql_db_backup_faster/__init__.py
mysql_db_backup_faster/version.py
mysql_db_backup_faster-0.1.0.data/scripts/mysqlbackup
tests/__init__.py
tests/base.py
tests/test_version.py
mysql_db_backup_faster-0.1.0.dist-info/METADATA
mysql_db_backup_faster-0.1.0.dist-info/WHEEL
mysql_db_backup_faster-0.1.0.dist-info/entry_points.txt
mysql_db_backup_faster-0.1.0.dist-info/top_level.txt
mysql_db_backup_faster-0.1.0.dist-info/RECORD
